LICENSE
LICENSE.txt
README.rst
setup.cfg
setup.py
gokuzen/__init__.py
gokuzen/gokuzen.py
gokuzen.egg-info/PKG-INFO
gokuzen.egg-info/SOURCES.txt
gokuzen.egg-info/dependency_links.txt
gokuzen.egg-info/top_level.txt