Metadata-Version: 2.1
Name: gokuzen
Version: 0.0.1
Summary: gokuzen is ?
Home-page: https://gokuzen.com
Author: gokuzen
Author-email: gokuzen@gmail.com
License: MIT
Download-URL: https://github.com/gokuzen/gokuzen.zip
Keywords: gokuzen
Platform: UNKNOWN
Classifier: Development Status :: 3 - Alpha
Classifier: Intended Audience :: Education
Classifier: Topic :: Utilities
Classifier: License :: OSI Approved :: MIT License
Classifier: Programming Language :: Python :: 3
Classifier: Programming Language :: Python :: 3.4
Classifier: Programming Language :: Python :: 3.5
Classifier: Programming Language :: Python :: 3.6
Classifier: Programming Language :: Python :: 3.7
Classifier: Programming Language :: Python :: 3.8
Classifier: Programming Language :: Python :: 3.9
Classifier: Programming Language :: Python :: 3.10
License-File: LICENSE
License-File: LICENSE.txt
